{
  "schema_version": "2.0",
  "entries": [
    {
      "timestamp": "2026-02-19T01:31:13.608366+00:00",
      "branch": "feat/service-infrastructure",
      "summary": "Configure Stitchery dev startup, switch Patchwork deps to NPM, and complete P1 verification",
      "decisions": "Use pnpm dlx @aprovan/stitchery and NPM patchwork packages",
      "modules": [
        "scripts/",
        "package.json",
        "pnpm-workspace.yaml",
        "apps/client/package.json",
        "apps/client/vite.config.ts",
        ".cicadas/active/stage-1-editing"
      ]
    }
  ]
}